ghostpeek/__init__.py
ghostpeek/__main__.py
ghostpeek/core.py
ghostpeek-1.1.1.dist-info/licenses/LICENSE
ghostpeek-1.1.1.dist-info/METADATA
ghostpeek-1.1.1.dist-info/WHEEL
ghostpeek-1.1.1.dist-info/entry_points.txt
ghostpeek-1.1.1.dist-info/top_level.txt
ghostpeek-1.1.1.dist-info/RECORD
