Metadata-Version: 2.4
Name: ghostpeek
Version: 1.1.1
Summary: A stealthy domain reconnaissance tool for subdomain discovery and intelligence gathering
Author-email: kaizoku73 <ultimate0134@gmail.com>
License: MIT
Project-URL: Homepage, https://github.com/kaizoku73/Ghostpeek
Project-URL: Documentation, https://github.com/kaizoku73/Ghostpeek#readme
Project-URL: Repository, https://github.com/kaizoku73/Ghostpeek.git
Project-URL: Bug Tracker, https://github.com/kaizoku73/Ghostpeek/issues
Keywords: reconnaissance,subdomain,security,pentesting,domain-analysis,whois,dns,osint,cybersecurity,web-scraping
Classifier: Development Status :: 4 - Beta
Classifier: Intended Audience :: Information Technology
Classifier: Intended Audience :: System Administrators
Classifier: License :: OSI Approved :: MIT License
Classifier: Operating System :: OS Independent
Classifier: Programming Language :: Python :: 3
Classifier: Programming Language :: Python :: 3.6
Classifier: Programming Language :: Python :: 3.7
Classifier: Programming Language :: Python :: 3.8
Classifier: Programming Language :: Python :: 3.9
Classifier: Programming Language :: Python :: 3.10
Classifier: Programming Language :: Python :: 3.11
Classifier: Programming Language :: Python :: 3.12
Classifier: Topic :: Security
Classifier: Topic :: Internet :: WWW/HTTP
Classifier: Topic :: System :: Networking :: Monitoring
Classifier: Topic :: System :: Systems Administration
Classifier: Environment :: Console
Requires-Python: >=3.6
License-File: LICENSE
Requires-Dist: aiohappyeyeballs==2.6.1
Requires-Dist: aiohttp==3.11.16
Requires-Dist: aioresponses==0.7.8
Requires-Dist: aiosignal==1.3.2
Requires-Dist: attrs==25.3.0
Requires-Dist: beautifulsoup4==4.13.3
Requires-Dist: certifi==2025.1.31
Requires-Dist: cffi==1.17.1
Requires-Dist: charset-normalizer==3.4.1
Requires-Dist: dnspython==2.7.0
Requires-Dist: frozenlist==1.5.0
Requires-Dist: h11==0.14.0
Requires-Dist: httpretty==1.1.4
Requires-Dist: idna==3.10
Requires-Dist: lxml==5.3.1
Requires-Dist: markdown-it-py==3.0.0
Requires-Dist: mdurl==0.1.2
Requires-Dist: multidict==6.2.0
Requires-Dist: outcome==1.3.0.post0
Requires-Dist: packaging==24.2
Requires-Dist: propcache==0.3.1
Requires-Dist: pycparser==2.22
Requires-Dist: Pygments==2.19.1
Requires-Dist: PySocks==1.7.1
Requires-Dist: python-dateutil==2.9.0.post0
Requires-Dist: python-Wappalyzer==0.3.1
Requires-Dist: python-whois==0.9.5
Requires-Dist: requests==2.32.3
Requires-Dist: rich==14.0.0
Requires-Dist: selenium==4.31.0
Requires-Dist: setuptools==79.0.0
Requires-Dist: six==1.17.0
Requires-Dist: sniffio==1.3.1
Requires-Dist: sortedcontainers==2.4.0
Requires-Dist: soupsieve==2.6
Requires-Dist: trio==0.29.0
Requires-Dist: trio-websocket==0.12.2
Requires-Dist: typing_extensions==4.13.0
Requires-Dist: urllib3==2.3.0
Requires-Dist: websocket-client==1.8.0
Requires-Dist: wsproto==1.2.0
Requires-Dist: yarl==1.18.3
Provides-Extra: dev
Requires-Dist: pytest>=7.0; extra == "dev"
Requires-Dist: pytest-cov>=4.0; extra == "dev"
Requires-Dist: black>=22.0; extra == "dev"
Requires-Dist: flake8>=5.0; extra == "dev"
Requires-Dist: mypy>=1.0; extra == "dev"
Dynamic: license-file
